LICENSE
README.md
setup.cfg
setup.py
django2_resumable/__init__.py
django2_resumable/fields.py
django2_resumable/files.py
django2_resumable/forms.py
django2_resumable/tests.py
django2_resumable/urls.py
django2_resumable/views.py
django2_resumable/widgets.py
django2_resumable.egg-info/PKG-INFO
django2_resumable.egg-info/SOURCES.txt
django2_resumable.egg-info/dependency_links.txt
django2_resumable.egg-info/not-zip-safe
django2_resumable.egg-info/requires.txt
django2_resumable.egg-info/top_level.txt