Metadata-Version: 2.1
Name: django2-resumable
Version: 0.1.1
Summary: Django 2.x resumable uploads
Home-page: https://github.com/leriomaggio/django2-resumable
Author: Valerio Maggio
Author-email: valeriomaggio@gmail.com
License: MIT licence
Platform: UNKNOWN
Classifier: Development Status :: 5 - Production/Stable
Classifier: Environment :: Web Environment
Classifier: Framework :: Django
Classifier: Intended Audience :: Developers
Classifier: License :: OSI Approved :: MIT License
Classifier: Natural Language :: English
Classifier: Programming Language :: Python
Classifier: Programming Language :: Python :: 3.7
